Workbook

Sheet 01_Instrucoes
A1: Context Pack RFY / SUPHO — Template de Coleta Estruturada
A2: Objetivo: permitir que o sistema gere insights e decisões mesmo sem CRM/ERP. Preencha as abas amarelas e faça o upload do arquivo no sistema.
A4: Como usar | B4: 1) Preencha primeiro as abas 02 a 07. 2) Se não houver CRM/ERP, preencha obrigatoriamente as abas 08, 09, 10, 13 e 16. 3) Se houver dados históricos/operacionais, preencha 11, 12 e 14. 4) Suba documentos de apoio na knowledge base e referencie-os nas abas 17 e 18.
A5: Mínimo viável sem CRM/ERP | B5: Identificação e contatos; objetivos/sponsors; processo comercial; pipeline manual; métricas de referência; unit economics; governança/rituais; documentos/evidências.
A6: O que o sistema vai usar | B6: O RFY cruza este template com o diagnóstico SUPHO, documentos da knowledge base e integrações (se existirem) para gerar: painel de maturidade, insights, plano 30/60/90, rituais e alertas.
A7: Cores | B7: Amarelo = preencher | Azul claro = explicação | Roxo = lógica/controle | Verde = calculado/ok | Laranja = atenção.
A8: Responsável pelo preenchimento | B8: Idealmente uma pessoa coordena o arquivo (sponsor/operações), pedindo informações para comercial, marketing, financeiro, tecnologia e liderança.
A10: Importante: CRM/ERP são apenas uma das fontes. O contexto real do cliente também precisa estar estruturado aqui para que o sistema produza números e decisões realistas.

Sheet 02_Identificacao_Contatos
A1: Identificação e contatos
A2: Preencha os dados básicos da organização, contatos-chave e responsáveis do projeto.
A4: Campo | B4: Valor | C4: Responsável interno | D4: Contato | E4: Observações | F4: Obrigatório? | G4: Status | H4: Data atualização
A5: Razão social | F5: Sim
A6: Nome fantasia | F6: Sim
A7: CNPJ | F7: Sim
A8: Site | F8: Não
A9: Segmento principal | F9: Sim
A10: ICP prioritário (Indústria / Tech-Serviços / Outro) | F10: Sim
A11: Cidade / Estado sede | F11: Sim
A12: Sponsor executivo | F12: Sim
A13: Responsável operacional do projeto | F13: Sim
A14: Responsável comercial | F14: Sim
A15: Responsável marketing | F15: Não
A16: Responsável financeiro | F16: Não
... A19: SLA interno de resposta (h úteis) | F19: Sim

Sheet 03_Objetivos_Sponsors
A1: Objetivos, sponsor e prioridades
A2: Use esta aba para dar contexto estratégico ao sistema.
A4: Tema | B4: Resposta | C4: Métrica/valor atual | D4: Meta 90 dias | E4: Meta 180 dias | F4: Responsável | G4: Prioridade | H4: Observações
A5: Objetivo principal do projeto em 1 frase
A6: O que seria sucesso em 90 dias
A7: O que seria sucesso em 180 dias
A8: 3 dores prioritárias que queremos resolver
A9: 3 riscos que mais preocupam hoje
A10: Decisões que estão travadas hoje
A11: Áreas mais impactadas (vendas, marketing, operação, financeiro, produto, RH, TI)
A12: Restrições importantes (caixa, time, prazo, tecnologia, compliance)

Sheet 04_Processo_Comercial
A1: Processo comercial e glossário
A2: Descreva como o cliente vende hoje, mesmo que o processo ainda seja manual.
A4: Tema | B4: Como funciona hoje | C4: Etapas/nomes | D4: Critério de passagem | E4: Dores/gargalos | F4: Owner | G4: Status | H4: Observações | I4: Documento/evidência
A5: ICP / personas prioritárias
A6: Oferta principal
A7: Oferta secundária / upsell
A8: Funil comercial (nomes das etapas)
A9: Definição de lead qualificado
A10: Definição de oportunidade
A11: Definição de proposta enviada
A12: Definição de venda fechada
A13: Objeções mais comuns
A14: Política de dados / privacidade / exclusividade
A15: Glossário interno (siglas e termos usados pela empresa)

Sheet 05_Perfil_Metricas
A1: Perfil e métricas de referência
A2: Informe os números-base para comparar antes/depois do piloto.
A4: Métrica | B4: Valor atual | C4: Fonte / como mede | D4: Periodicidade | E4: Meta 90 dias | F4: Meta 180 dias | G4: Responsável | H4: Observações
A5: Receita mensal média
A6: Receita últimos 12 meses
A7: Ticket médio
A8: Prazo médio de recebimento
A9: Cobertura de pipeline
A10: Tempo de ciclo comercial (dias)
A11: Win rate (%)
A12: Nº reuniões/mês
A13: Nº propostas/mês
A14: Nº vendas/mês
A15: Capacidade operacional (projetos/mês)
A16: NPS / satisfação (se existir)
... A18: Churn (se existir assinatura)

Sheet 06_Config_Operacional
A1: Configuração operacional e alertas
A2: Defina rotina, SLAs, limites e alertas para o sistema entender a operação.
A4: Tema | B4: Configuração atual | C4: Limite / regra | D4: Canal do alerta | E4: Responsável | F4: Status | G4: Observações | H4: Documento/evidência
A5: SLA resposta lead
A6: SLA resposta cliente
A7: SLA entrega projeto/POC
A8: Capacidade máxima de projetos simultâneos
A9: O que caracteriza atraso
A10: O que caracteriza deal crítico
A11: Tempo sem atividade para virar fricção
A12: A quem alertar em caso crítico
A13: Ritual semanal atual
A14: Ritual executivo mensal atual

Sheet 07_Integracoes_Dados
A1: Integrações, sistemas e fontes de dados
A2: Liste o que existe hoje e qual o grau de confiabilidade. Não precisa estar 100% integrado.
A4: Fonte/Sistema | B4: Tipo | C4: Situação | D4: Principal uso | E4: Dados disponíveis | F4: Última atualização | G4: Owner | H4: Exporta CSV? | I4: Integrado hoje? | J4: Observações
A5: CRM
A6: ERP
A7: Financeiro/Conta azul/Omie/etc.
A8: Planilha comercial
A9: Ferramenta de e-mail
A10: Ferramenta de automação
A11: BI / Dashboard
A12: Plataforma do produto
A13: Banco de dados
A14: Outros

Sheet 08_Pipeline_Manual
A1: Pipeline manual (substitui CRM quando necessário)
A2: Preencha uma linha por conta/oportunidade ativa. O sistema usará estas informações caso não exista CRM integrado.
A3: Se a empresa tiver CRM ativo, esta aba pode ser opcional. Se não tiver CRM, esta aba é obrigatória.
A4: Conta / Cliente | B4: Contato principal | C4: Segmento/ICP | D4: Produto/Oferta | E4: Etapa atual | F4: Valor estimado (R$) | G4: Probabilidade (%) | H4: Última interação | I4: Próxima ação | J4: Data próxima ação | K4: Risco principal | L4: Owner

Sheet 09_Campanhas_Canais
A1: Campanhas, canais e resultados
A2: Use uma linha por campanha, outreach ou ação relevante.
A4: Campanha/Ação | B4: Canal | C4: Período | D4: Público | E4: Objetivo | F4: Entregues/alcance | G4: Abertura (%) | H4: Cliques (%) | I4: Respostas/Reuniões | J4: Vendas | K4: Observações

Sheet 10_UnitEconomics
A1: Unit economics / oferta principal
A2: Preencha custos e premissas da oferta principal. As células verdes são calculadas.
A4: Categoria | B4: Item de custo | C4: Descrição | D4: Unidade | E4: Qtd por projeto | F4: Valor unitário (R$) | G4: Custo total (R$) | H4: Observações
A5: Custos diretos | B5: Embalagem / acondicionamento | D5: por respondente | G5: =IFERROR(E5*F5,0) -> 0
A6: Custos diretos | B6: Manuseio / operação | D6: por projeto | G6: =IFERROR(E6*F6,0) -> 0
A7: Custos diretos | B7: Entrega / logística | D7: por respondente | G7: =IFERROR(E7*F7,0) -> 0
A8: Custos diretos | B8: Brindes / incentivos | D8: por respondente | G8: =IFERROR(E8*F8,0) -> 0
A9: Ferramentas | B9: Pesquisa / formulário | D9: mensal rateado | G9: =IFERROR(E9*F9,0) -> 0
A10: Ferramentas | B10: Mensageria / e-mail / WhatsApp | D10: mensal rateado | G10: =IFERROR(E10*F10,0) -> 0
A11: Horas internas | B11: Responsável principal | D11: horas | G11: =IFERROR(E11*F11,0) -> 0
A12: Horas internas | B12: Apoio operacional | D12: horas | G12: =IFERROR(E12*F12,0) -> 0
A13: Tecnologia | B13: Desenvolvimento / manutenção | D13: horas/mês | G13: =IFERROR(E13*F13,0) -> 0
A14: Tecnologia | B14: Infraestrutura / hospedagem | D14: mensal | G14: =IFERROR(E14*F14,0) -> 0
A15: Aquisição | B15: Tráfego / recrutamento pago | D15: por projeto | G15: =IFERROR(E15*F15,0) -> 0
A18: Premissas do projeto
A19: Nº de respondentes planejados
A20: Preço cobrado por projeto (R$)
A21: Receita líquida estimada (R$)
A23: KPIs calculados
A24: Custo total do projeto | B24: =SUM(G5:G15) -> 0
A25: Custo por respondente
A26: Margem bruta (R$) | B26: =IFERROR(B20-B24,0) -> 0
A27: Margem bruta (%) | B27: =IFERROR(B26/B20,0) -> 0

Sheet 11_Recrutamento_Filtros
A1: Recrutamento e filtros por categoria/projeto
A2: Preencha uma linha por categoria/projeto com o funil operacional. Isso ajuda o sistema a gerar benchmarks internos e previsibilidade.
A4: Categoria / projeto | B4: Cidade / região | C4: Critérios de filtro usados | D4: Base ativada (#) | E4: Responderam filtro (#) | F4: Elegíveis (#) | G4: Receberam kit (#) | H4: Responderam pesquisa final (#) | I4: Taxa resposta filtro | J4: Taxa elegibilidade | K4: Taxa resposta final
I5: =IFERROR(E5/D5,0) -> 0 | J5: =IFERROR(F5/E5,0) -> 0 | K5: =IFERROR(H5/G5,0) -> 0
I6: =IFERROR(E6/D6,0) -> 0 | J6: =IFERROR(F6/E6,0) -> 0 | K6: =IFERROR(H6/G6,0) -> 0
I7: =IFERROR(E7/D7,0) -> 0 | J7: =IFERROR(F7/E7,0) -> 0 | K7: =IFERROR(H7/G7,0) -> 0
I8: =IFERROR(E8/D8,0) -> 0 | J8: =IFERROR(F8/E8,0) -> 0 | K8: =IFERROR(H8/G8,0) -> 0
I9: =IFERROR(E9/D9,0) -> 0 | J9: =IFERROR(F9/E9,0) -> 0 | K9: =IFERROR(H9/G9,0) -> 0
I10: =IFERROR(E10/D10,0) -> 0 | J10: =IFERROR(F10/E10,0) -> 0 | K10: =IFERROR(H10/G10,0) -> 0
I11: =IFERROR(E11/D11,0) -> 0 | J11: =IFERROR(F11/E11,0) -> 0 | K11: =IFERROR(H11/G11,0) -> 0
I12: =IFERROR(E12/D12,0) -> 0 | J12: =IFERROR(F12/E12,0) -> 0 | K12: =IFERROR(H12/G12,0) -> 0
I13: =IFERROR(E13/D13,0) -> 0 | J13: =IFERROR(F13/E13,0) -> 0 | K13: =IFERROR(H13/G13,0) -> 0
I14: =IFERROR(E14/D14,0) -> 0 | J14: =IFERROR(F14/E14,0) -> 0 | K14: =IFERROR(H14/G14,0) -> 0
I15: =IFERROR(E15/D15,0) -> 0 | J15: =IFERROR(F15/E15,0) -> 0 | K15: =IFERROR(H15/G15,0) -> 0
I16: =IFERROR(E16/D16,0) -> 0 | J16: =IFERROR(F16/E16,0) -> 0 | K16: =IFERROR(H16/G16,0) -> 0
... I29: =IFERROR(E29/D29,0) -> 0 | J29: =IFERROR(F29/E29,0) -> 0 | K29: =IFERROR(H29/G29,0) -> 0

Sheet 12_Base_Logistica
A1: Base por cidade e viabilidade logística
A2: Use esta aba para registrar bases locais, categorias com massa crítica e custos/prazos logísticos.
A4: Cidade / polo | B4: Tamanho da base | C4: Categorias com base suficiente | D4: Parceiro logístico / operação | E4: Custo estimado por entrega (R$) | F4: Prazo / SLA estimado | G4: Responsável | H4: Observações

Sheet 13_Mapa_Fiscal_Fin
A1: Mapa fiscal e financeiro
A2: Registre regime, CNAEs, alíquotas e premissas financeiras que impactam precificação e narrativa do produto.
A4: Tema | B4: Informação atual | C4: Onde buscar / quem confirma | D4: Impacto no diagnóstico | E4: Status | F4: Observações | G4: Link / evidência | H4: Data
A5: Regime tributário
A6: CNAE principal atual
A7: CNAEs secundários relevantes
A8: Anexo do Simples
A9: Alíquota efetiva média
A10: Tipo de receita atual
A11: Hipótese para tecnologia / assinatura
A12: Risco / limitação fiscal
A13: Prazo médio real de recebimento
A14: Receita últimos 12 meses
A15: Receita por linha de produto
A16: Custos fixos mensais

Sheet 14_Tecnologia_Roadmap
A1: Tecnologia, stack, dependências e roadmap
A2: Preencha o estado atual dos módulos, custos de terceiros e dependências técnicas.
A4: Tema | B4: Estado atual | C4: Ferramenta / stack | D4: Custo mensal estimado | E4: Dependências | F4: Próximo passo | G4: Responsável | H4: Prioridade | I4: Observações
A5: Plataforma principal
A6: Dashboard / BI
A7: Diagnóstico / formulários
A8: Automação / jobs
A9: Alertas e relatórios
A10: Billing / cobrança
A11: IA / embeddings / tokens
A12: Social listening
A13: SSO / permissões
A14: Integrações (CRM/ERP)
A15: Observabilidade / logs

Sheet 15_Governanca_Politicas
A1: Governança, RBAC e políticas
A2: Use esta aba para mapear donos, papéis e políticas que afetam a execução e a segurança.
A4: Tema | B4: Como funciona hoje | C4: Dono/Owner | D4: Periodicidade | E4: Status | F4: Risco se faltar | G4: Observações | H4: Documento/evidência
A5: Ritual semanal operacional
A6: Ritual executivo mensal
A7: Acompanhamento do plano 30/60/90
A8: Registro de decisões
A9: Papéis e permissões de acesso
A10: Política de dados / privacidade
A11: Política de segurança / backup
A12: Aprovação de propostas / descontos
A13: Aprovação de investimentos / compras

Sheet 16_Rituais_PAIP
A1: Rituais, decisões e vínculo com o plano 30/60/90
A2: Cada decisão relevante deve virar ação no plano. Use uma linha por decisão/ação.
A4: Ritual/Data | B4: Tema | C4: Decisão tomada | D4: Ação vinculada | E4: Janela do plano (30/60/90) | F4: Responsável | G4: Prazo | H4: Status | I4: Impacto esperado | J4: Observações

Sheet 17_Acessos_Arquivos
A1: Acessos, arquivos e knowledge base
A2: Liste os acessos e documentos que sustentam o contexto da organização.
A4: Tipo | B4: Item | C4: Descrição | D4: Quem libera | E4: Formato esperado | F4: Prazo | G4: Status | H4: Observações

Sheet 18_Status_Projeto
A1: Status atual do projeto e dos módulos
A2: Use para registrar estágio atual, previsões, custos de terceiros e dependências.
A4: Módulo / frente | B4: Status atual | C4: Escopo desta fase | D4: Previsão de entrega | E4: Riscos / dependências | F4: Custo de terceiros mapeado? | G4: Responsável | H4: Observações
A5: Integração CRM/ERP
A6: Diagnóstico SUPHO
A7: Alertas e relatórios
A8: Billing
A9: Rituais / decisões / PAIP
A10: Base de conhecimento / IA
A11: Painel de previsões
A12: Social listening
A13: Permissões avançadas / SSO

Sheet 19_Resumo_Completude
A1: Resumo de completude do Context Pack
A2: As fórmulas abaixo ajudam a verificar se o pacote tem informação suficiente para gerar insights confiáveis.
A4: Seção | B4: Planilha | C4: Campos-chave preenchidos | D4: Campos esperados | E4: % completude | F4: Obrigatória sem CRM? | G4: Status sugerido
A5: Identificação e contatos | B5: 02_Identificacao_Contatos | C5: =COUNTA('02_Identificacao_Contatos'!B5:B19) -> 0 | D5: 15 | E5: =IFERROR(C5/D5,0) -> 0 | F5: Sim | G5: =IF(E5>=0.8,"Alta",IF(E5>=0.5,"Média","Baixa")) -> Baixa
A6: Objetivos e sponsors | B6: 03_Objetivos_Sponsors | C6: =COUNTA('03_Objetivos_Sponsors'!B5:B12) -> 0 | D6: 8 | E6: =IFERROR(C6/D6,0) -> 0 | F6: Sim | G6: =IF(E6>=0.8,"Alta",IF(E6>=0.5,"Média","Baixa")) -> Baixa
A7: Processo comercial | B7: 04_Processo_Comercial | C7: =COUNTA('04_Processo_Comercial'!B5:B15) -> 0 | D7: 11 | E7: =IFERROR(C7/D7,0) -> 0 | F7: Sim | G7: =IF(E7>=0.8,"Alta",IF(E7>=0.5,"Média","Baixa")) -> Baixa
A8: Perfil e métricas | B8: 05_Perfil_Metricas | C8: =COUNTA('05_Perfil_Metricas'!B5:B18) -> 0 | D8: 14 | E8: =IFERROR(C8/D8,0) -> 0 | F8: Sim | G8: =IF(E8>=0.8,"Alta",IF(E8>=0.5,"Média","Baixa")) -> Baixa
A9: Config operacional | B9: 06_Config_Operacional | C9: =COUNTA('06_Config_Operacional'!B5:B14) -> 0 | D9: 10 | E9: =IFERROR(C9/D9,0) -> 0 | F9: Sim | G9: =IF(E9>=0.8,"Alta",IF(E9>=0.5,"Média","Baixa")) -> Baixa
A10: Integrações e dados | B10: 07_Integracoes_Dados | C10: =COUNTA('07_Integracoes_Dados'!B5:B14) -> 0 | D10: 10 | E10: =IFERROR(C10/D10,0) -> 0 | F10: Não | G10: =IF(E10>=0.8,"Alta",IF(E10>=0.5,"Média","Baixa")) -> Baixa
A11: Pipeline manual | B11: 08_Pipeline_Manual | C11: =COUNTA('08_Pipeline_Manual'!A5:A44) -> 0 | D11: 40 | E11: =IFERROR(C11/D11,0) -> 0 | F11: Sim | G11: =IF(E11>=0.8,"Alta",IF(E11>=0.5,"Média","Baixa")) -> Baixa
A12: Campanhas/canais | B12: 09_Campanhas_Canais | C12: =COUNTA('09_Campanhas_Canais'!A5:A24) -> 0 | D12: 20 | E12: =IFERROR(C12/D12,0) -> 0 | F12: Não | G12: =IF(E12>=0.8,"Alta",IF(E12>=0.5,"Média","Baixa")) -> Baixa
A13: Unit economics | B13: 10_UnitEconomics | C13: =COUNTA('10_UnitEconomics'!C5:C15)+COUNTA('10_UnitEconomics'!E5:E15)+COUNTA('10_UnitEconomics'!F5:F15)+COUNTA('10_UnitEconomics'!B18:B20) -> 0 | D13: 36 | E13: =IFERROR(C13/D13,0) -> 0 | F13: Sim | G13: =IF(E13>=0.8,"Alta",IF(E13>=0.5,"Média","Baixa")) -> Baixa
A14: Recrutamento/filtros | B14: 11_Recrutamento_Filtros | C14: =COUNTA('11_Recrutamento_Filtros'!A5:A29) -> 0 | D14: 25 | E14: =IFERROR(C14/D14,0) -> 0 | F14: Não | G14: =IF(E14>=0.8,"Alta",IF(E14>=0.5,"Média","Baixa")) -> Baixa
A15: Base/logística | B15: 12_Base_Logistica | C15: =COUNTA('12_Base_Logistica'!A5:A19) -> 0 | D15: 15 | E15: =IFERROR(C15/D15,0) -> 0 | F15: Não | G15: =IF(E15>=0.8,"Alta",IF(E15>=0.5,"Média","Baixa")) -> Baixa
A16: Mapa fiscal | B16: 13_Mapa_Fiscal_Fin | C16: =COUNTA('13_Mapa_Fiscal_Fin'!B5:B16) -> 0 | D16: 12 | E16: =IFERROR(C16/D16,0) -> 0 | F16: Sim | G16: =IF(E16>=0.8,"Alta",IF(E16>=0.5,"Média","Baixa")) -> Baixa
A17: Tecnologia/roadmap | B17: 14_Tecnologia_Roadmap | C17: =COUNTA('14_Tecnologia_Roadmap'!B5:B15) -> 0 | D17: 11 | E17: =IFERROR(C17/D17,0) -> 0 | F17: Não | G17: =IF(E17>=0.8,"Alta",IF(E17>=0.5,"Média","Baixa")) -> Baixa
A18: Governança/políticas | B18: 15_Governanca_Politicas | C18: =COUNTA('15_Governanca_Politicas'!B5:B13) -> 0 | D18: 9 | E18: =IFERROR(C18/D18,0) -> 0 | F18: Sim | G18: =IF(E18>=0.8,"Alta",IF(E18>=0.5,"Média","Baixa")) -> Baixa
A19: Rituais/PAIP | B19: 16_Rituais_PAIP | C19: =COUNTA('16_Rituais_PAIP'!A5:A34) -> 0 | D19: 30 | E19: =IFERROR(C19/D19,0) -> 0 | F19: Sim | G19: =IF(E19>=0.8,"Alta",IF(E19>=0.5,"Média","Baixa")) -> Baixa
A20: Acessos/arquivos | B20: 17_Acessos_Arquivos | C20: =COUNTA('17_Acessos_Arquivos'!A5:A24) -> 0 | D20: 20 | E20: =IFERROR(C20/D20,0) -> 0 | F20: Não | G20: =IF(E20>=0.8,"Alta",IF(E20>=0.5,"Média","Baixa")) -> Baixa
A23: Completude geral | C23: =SUM(C5:C20) -> 0 | D23: =SUM(D5:D20) -> 0 | E23: =IFERROR(C23/D23,0) -> 0 | G23: =IF(E23>=0.8,"Pronto para insights","Parcial / complementar contexto") -> Parcial / complementar contexto
A25: Regra sugerida para pilotos: se não houver CRM/ERP, considerar contexto suficiente quando a completude geral for >=80% e todas as seções obrigatórias estiverem em Alta ou Média.
